ldh_operator/__init__.py
ldh_operator/basic.py
ldh_operator/data/deckplan.yaml
ldh_operator/data/default.yaml
ldh_operator-0.0.5.data/scripts/whipstaff.py
ldh_operator-0.0.5.dist-info/COPYING.AGPL.md
ldh_operator-0.0.5.dist-info/METADATA
ldh_operator-0.0.5.dist-info/WHEEL
ldh_operator-0.0.5.dist-info/entry_points.txt
ldh_operator-0.0.5.dist-info/top_level.txt
ldh_operator-0.0.5.dist-info/RECORD
