Metadata-Version: 2.1
Name: ldh-operator
Version: 0.0.5
Summary: Whipstaff is a command-line tool for operating one or more Liberty Deckplan Hosts (LDHs) from your local session. The reference implementation for an LDH operator toolkit.
Home-page: https://source.puri.sm/liberty/tool/operator
Author: Purism SPC
Author-email: doublerainbows@librem.one
License: AGPL-3.0-or-later
Platform: UNKNOWN
Classifier: Programming Language :: Python :: 3
Classifier: Programming Language :: Python :: 3.7
Classifier: License :: OSI Approved :: GNU Affero General Public License v3 or later (AGPLv3+)
Requires-Dist: click (<=7.0)
Requires-Dist: distro (<=1.3.0)
Requires-Dist: strictyaml (<=1.0.6)
Requires-Dist: sh (<=1.12.14)
